<?xml version="1.0" encoding="utf-16" ?>
<SpecialOffer>
<Row SpecialOfferID="1" Description="No Discount" DiscountPct="0.00" Type="No Discount" Category="No Discount" StartDate="Jun  1 2005 12:00AM" EndDate="Dec 31 2008 12:00AM" MinQty="0" MaxQty="" rowguid="0290C4F5-191F-4337-AB6B-0A2DDE03CBF9" ModifiedDate="May  2 2005 12:00AM"/>
<Row SpecialOfferID="2" Description="Volume Discount 11 to 14" DiscountPct="0.02" Type="Volume Discount" Category="Reseller" StartDate="Jul  1 2005 12:00AM" EndDate="Jun 30 2008 12:00AM" MinQty="11" MaxQty="14" rowguid="D7542EE7-15DB-4541-985C-5CC27AEF26D6" ModifiedDate="Jun  1 2005 12:00AM"/>
<Row SpecialOfferID="3" Description="Volume Discount 15 to 24" DiscountPct="0.05" Type="Volume Discount" Category="Reseller" StartDate="Jul  1 2005 12:00AM" EndDate="Jun 30 2008 12:00AM" MinQty="15" MaxQty="24" rowguid="4BDBCC01-8CF7-40A9-B643-40EC5B717491" ModifiedDate="Jun  1 2005 12:00AM"/>
<Row SpecialOfferID="4" Description="Volume Discount 25 to 40" DiscountPct="0.10" Type="Volume Discount" Category="Reseller" StartDate="Jul  1 2005 12:00AM" EndDate="Jun 30 2008 12:00AM" MinQty="25" MaxQty="40" rowguid="504B5E85-8F3F-4EBC-9E1D-C1BC5DEA9AA8" ModifiedDate="Jun  1 2005 12:00AM"/>
<Row SpecialOfferID="5" Description="Volume Discount 41 to 60" DiscountPct="0.15" Type="Volume Discount" Category="Reseller" StartDate="Jul  1 2005 12:00AM" EndDate="Jun 30 2008 12:00AM" MinQty="41" MaxQty="60" rowguid="677E1D9D-944F-4E81-90E8-47EB0A82D48C" ModifiedDate="Jun  1 2005 12:00AM"/>
<Row SpecialOfferID="6" Description="Volume Discount over 60" DiscountPct="0.20" Type="Volume Discount" Category="Reseller" StartDate="Jul  1 2005 12:00AM" EndDate="Jun 30 2008 12:00AM" MinQty="61" MaxQty="" rowguid="8157F569-4E8D-46B6-9347-5D0F726A9439" ModifiedDate="Jun  1 2005 12:00AM"/>
<Row SpecialOfferID="7" Description="Mountain-100 Clearance Sale" DiscountPct="0.35" Type="Discontinued Product" Category="Reseller" StartDate="May 15 2006 12:00AM" EndDate="Jun 30 2006 12:00AM" MinQty="0" MaxQty="" rowguid="7DF15BF5-6C05-47E7-80A4-22BD1CE59A72" ModifiedDate="Apr 15 2006 12:00AM"/>
<Row SpecialOfferID="8" Description="Sport Helmet Discount-2002" DiscountPct="0.10" Type="Seasonal Discount" Category="Reseller" StartDate="Jul  1 2006 12:00AM" EndDate="Jul 31 2006 12:00AM" MinQty="0" MaxQty="" rowguid="20C5D2CC-A38F-48F8-AC9A-8F15943E52AE" ModifiedDate="Jun  1 2006 12:00AM"/>
<Row SpecialOfferID="9" Description="Road-650 Overstock" DiscountPct="0.30" Type="Excess Inventory" Category="Reseller" StartDate="Jul  1 2006 12:00AM" EndDate="Aug 31 2006 12:00AM" MinQty="0" MaxQty="" rowguid="0CF8472B-F9E6-4945-9E09-549D7DDE2198" ModifiedDate="Jun  1 2006 12:00AM"/>
<Row SpecialOfferID="10" Description="Mountain Tire Sale" DiscountPct="0.50" Type="Excess Inventory" Category="Customer" StartDate="Jun 15 2007 12:00AM" EndDate="Aug 30 2007 12:00AM" MinQty="0" MaxQty="" rowguid="220444AD-2EF3-4E4C-87E9-3AA6EE39A877" ModifiedDate="May 16 2007 12:00AM"/>
<Row SpecialOfferID="11" Description="Sport Helmet Discount-2003" DiscountPct="0.15" Type="Seasonal Discount" Category="Reseller" StartDate="Jul  1 2007 12:00AM" EndDate="Jul 31 2007 12:00AM" MinQty="0" MaxQty="" rowguid="E72DAB1D-F44D-448B-9FE2-F259A2F0210D" ModifiedDate="Jun  1 2007 12:00AM"/>
<Row SpecialOfferID="12" Description="LL Road Frame Sale" DiscountPct="0.35" Type="Excess Inventory" Category="Reseller" StartDate="Jul  1 2007 12:00AM" EndDate="Aug 15 2007 12:00AM" MinQty="0" MaxQty="" rowguid="C0AF1C89-9722-4235-9248-3FBA4D9E5841" ModifiedDate="Jun  1 2007 12:00AM"/>
<Row SpecialOfferID="13" Description="Touring-3000 Promotion" DiscountPct="0.15" Type="New Product" Category="Reseller" StartDate="Jul  1 2007 12:00AM" EndDate="Sep 30 2007 12:00AM" MinQty="0" MaxQty="" rowguid="5061CCE4-E021-45A8-9A75-DFB36CBBCE85" ModifiedDate="Jun  1 2007 12:00AM"/>
<Row SpecialOfferID="14" Description="Touring-1000 Promotion" DiscountPct="0.20" Type="New Product" Category="Reseller" StartDate="Jul  1 2007 12:00AM" EndDate="Sep 30 2007 12:00AM" MinQty="0" MaxQty="" rowguid="1AF84A9E-A98C-4BD9-B48F-DC2B8B6B010B" ModifiedDate="Jun  1 2007 12:00AM"/>
<Row SpecialOfferID="15" Description="Half-Price Pedal Sale" DiscountPct="0.50" Type="Seasonal Discount" Category="Customer" StartDate="Aug 15 2007 12:00AM" EndDate="Sep 15 2007 12:00AM" MinQty="0" MaxQty="" rowguid="03E3594D-6EBB-46A6-B8EE-A9289C0C2E47" ModifiedDate="Jul 16 2007 12:00AM"/>
<Row SpecialOfferID="16" Description="Mountain-500 Silver Clearance Sale" DiscountPct="0.40" Type="Discontinued Product" Category="Reseller" StartDate="May  1 2008 12:00AM" EndDate="Jun 30 2008 12:00AM" MinQty="0" MaxQty="" rowguid="EB7CB484-BCCF-4D2D-BF73-521B20014174" ModifiedDate="Apr  1 2008 12:00AM"/>
</SpecialOffer>

